modelasv/__init__.py
modelasv/analyzer.py
modelasv/simulator.py
modelasv/utils.py
modelasv/hardware_model/__init__.py
modelasv/hardware_model/roofline_model.py
modelasv/nn/__init__.py
modelasv/nn/attn.py
modelasv/nn/conv.py
modelasv/nn/embedding.py
modelasv/nn/linear.py
modelasv/nn/norm.py
modelasv/nn/register.py
modelasv/nn/utils.py
modelasv-0.2.dist-info/LICENSE
modelasv-0.2.dist-info/METADATA
modelasv-0.2.dist-info/WHEEL
modelasv-0.2.dist-info/top_level.txt
modelasv-0.2.dist-info/RECORD
